imu_listener/__init__.py
imu_listener/imu_listener.py
imu_listener-1.0.0.dist-info/LICENSE
imu_listener-1.0.0.dist-info/METADATA
imu_listener-1.0.0.dist-info/WHEEL
imu_listener-1.0.0.dist-info/top_level.txt
imu_listener-1.0.0.dist-info/RECORD
