Metadata-Version: 2.1
Name: imu-listener
Version: 1.0.0
Summary: ROS package for receiving IMU data from a RealSense camera using rospy
Home-page: https://github.com/divagarn/imu_listener
Author: Divagar N
Author-email: divagar2kn@gmail.com
License: MIT
Keywords: ROS,IMU,RealSense,rospy
License-File: LICENSE
